krb5/_kt.cpython-311-darwin.so
krb5/_principal_heimdal.pyi
krb5/_kt.pyi
krb5/_keyblock_mit.pyi
krb5/_context.pyi
krb5/_string.pyi
krb5/_ccache_support_switch.cpython-311-darwin.so
krb5/_creds_opt_set_pac_request.cpython-311-darwin.so
krb5/_cccol.cpython-311-darwin.so
krb5/_chpw_message_mit.pyi
krb5/_string.cpython-311-darwin.so
krb5/_kt_heimdal.pyi
krb5/_ccache_mit.pyi
krb5/_context_mit.pyi
krb5/_keyblock.cpython-311-darwin.so
krb5/_creds_mit.pyi
krb5/_creds_opt.pyi
krb5/_ccache_match.pyi
krb5/_context.cpython-311-darwin.so
krb5/_creds_opt_set_in_ccache.pyi
krb5/__init__.py
krb5/_ccache_support_switch.pyi
krb5/_ccache_match.cpython-311-darwin.so
krb5/_adpi.py
krb5/_exceptions.pyi
krb5/_exceptions.cpython-311-darwin.so
krb5/_string_mit.pyi
krb5/_kt_have_content.pyi
krb5/_kt_have_content.cpython-311-darwin.so
krb5/_kt_heimdal.cpython-311-darwin.so
krb5/_principal.cpython-311-darwin.so
krb5/_creds_opt_set_pac_request.pyi
krb5/_creds_opt_heimdal.cpython-311-darwin.so
krb5/_set_password.cpython-311-darwin.so
krb5/_cccol.pyi
krb5/_creds.cpython-311-darwin.so
krb5/_creds_marshal_mit.pyi
krb5/py.typed
krb5/_creds_opt_heimdal.pyi
krb5/_kt_mit.pyi
krb5/_principal.pyi
krb5/_ccache.cpython-311-darwin.so
krb5/_ccache.pyi
krb5/_principal_heimdal.cpython-311-darwin.so
krb5/_keyblock.pyi
krb5/_creds_opt_mit.pyi
krb5/_set_password.pyi
krb5/_creds_opt.cpython-311-darwin.so
krb5/_creds.pyi
krb5-0.7.1.dist-info/RECORD
krb5-0.7.1.dist-info/LICENSE
krb5-0.7.1.dist-info/WHEEL
krb5-0.7.1.dist-info/top_level.txt
krb5-0.7.1.dist-info/METADATA
