Metadata-Version: 2.2
Name: krb5
Version: 0.7.1
Summary: Kerberos API bindings for Python
Home-page: https://github.com/jborean93/pykrb5
Author: Jordan Borean
Author-email: jborean93@gmail.com
License: MIT
Keywords: krb5,kerberos
Classifier: Development Status :: 4 - Beta
Classifier: License :: OSI Approved :: MIT License
Classifier: Programming Language :: Python :: 3
Classifier: Programming Language :: Python :: 3.8
Classifier: Programming Language :: Python :: 3.9
Classifier: Programming Language :: Python :: 3.10
Classifier: Programming Language :: Python :: 3.11
Classifier: Programming Language :: Python :: 3.12
Classifier: Programming Language :: Python :: 3.13
Requires-Python: >=3.8
License-File: LICENSE
